<?xml version="1.0" encoding="utf-8" ?>
<dwsync>
<file name="yoga.jpg" server="romrvc.com" local="131489506047889234" remote="131489560200000000" Dst="0" />
<file name="fitness.jpg" server="romrvc.com" local="131489507374829796" remote="131489560200000000" Dst="0" />
<file name="bodybuilding.jpg" server="romrvc.com" local="131489506468395136" remote="131489560200000000" Dst="0" />
<file name="choose_us.jpg" server="romrvc.com" local="131489527243936226" remote="131489560200000000" Dst="0" />
<file name="boxing.jpg" server="romrvc.com" local="131489508646973832" remote="131489560200000000" Dst="0" />
<file name="section_one.jpg" server="romrvc.com" local="131484497058180623" remote="131489560200000000" Dst="0" />
<file name="gym_room.jpg" server="romrvc.com" local="131489546260720234" remote="131489560200000000" Dst="0" />
<file name="powerlifting_trainer.jpg" server="romrvc.com" local="131489536245188177" remote="131489560200000000" Dst="0" />
<file name="yoga_trainer.jpg" server="romrvc.com" local="131489544282907507" remote="131489560200000000" Dst="0" />
<file name="boxing_trainer.jpg" server="romrvc.com" local="131489540196224305" remote="131489560200000000" Dst="0" />
<file name="fitness_trainer.jpg" server="romrvc.com" local="131489537805713632" remote="131489560200000000" Dst="0" />
</dwsync>